autothemewin10/__init__.py
autothemewin10/main.py
autothemewin10-1.0.0.dist-info/entry_points.txt
autothemewin10-1.0.0.dist-info/LICENSE
autothemewin10-1.0.0.dist-info/WHEEL
autothemewin10-1.0.0.dist-info/METADATA
autothemewin10-1.0.0.dist-info/RECORD
